{
  "main": {
    "id": "296ab50dc8ff0736",
    "type": "split",
    "children": [
      {
        "id": "979c170377bbd77d",
        "type": "tabs",
        "children": [
          {
            "id": "9de8b62bb5cbb4ee",
            "type": "leaf",
            "state": {
              "type": "markdown",
              "state": {
                "file": "개발/스프링과 DI/스프링과 DI.md",
                "mode": "source",
                "source": false
              },
              "icon": "lucide-file",
              "title": "스프링과 DI"
            }
          },
          {
            "id": "828dd042d4e94151",
            "type": "leaf",
            "state": {
              "type": "markdown",
              "state": {
                "file": "개발/스프링을 잘한다의 정의.md",
                "mode": "source",
                "source": false
              },
              "icon": "lucide-file",
              "title": "스프링을 잘한다의 정의"
            }
          },
          {
            "id": "88f5be8b5db62ca4",
            "type": "leaf",
            "state": {
              "type": "markdown",
              "state": {
                "file": "서비스 디자이너/RNR.md",
                "mode": "source",
                "source": false
              },
              "icon": "lucide-file",
              "title": "RNR"
            }
          },
          {
            "id": "cc990617e5bfac50",
            "type": "leaf",
            "state": {
              "type": "markdown",
              "state": {
                "file": "서비스 디자이너/JD.md",
                "mode": "source",
                "source": false
              },
              "icon": "lucide-file",
              "title": "JD"
            }
          },
          {
            "id": "8f96d653403f0d82",
            "type": "leaf",
            "state": {
              "type": "markdown",
              "state": {
                "file": "서비스 디자이너/JD.md",
                "mode": "source",
                "source": false
              },
              "icon": "lucide-file",
              "title": "JD"
            }
          },
          {
            "id": "2ce7448a7c38cbf9",
            "type": "leaf",
            "state": {
              "type": "markdown",
              "state": {
                "file": "개발/스프링과 DI/스프링과 DI Map.md",
                "mode": "source",
                "source": false
              },
              "icon": "lucide-file",
              "title": "스프링과 DI Map"
            }
          }
        ],
        "currentTab": 3
      },
      {
        "id": "53c468e4fed1fe69",
        "type": "tabs",
        "children": [
          {
            "id": "8846d4e84ccf067b",
            "type": "leaf",
            "state": {
              "type": "markdown",
              "state": {
                "file": "서비스 디자이너/JD.md",
                "mode": "preview",
                "source": false
              },
              "icon": "lucide-file",
              "title": "JD"
            }
          }
        ]
      }
    ],
    "direction": "vertical"
  },
  "left": {
    "id": "0d0853d96bc909d3",
    "type": "split",
    "children": [
      {
        "id": "363eafe554ccb273",
        "type": "tabs",
        "children": [
          {
            "id": "0a039d460ae22e11",
            "type": "leaf",
            "state": {
              "type": "file-explorer",
              "state": {
                "sortOrder": "alphabetical"
              },
              "icon": "lucide-folder-closed",
              "title": "Files"
            }
          },
          {
            "id": "03e267dfc2f089dc",
            "type": "leaf",
            "state": {
              "type": "search",
              "state": {
                "query": "",
                "matchingCase": false,
                "explainSearch": false,
                "collapseAll": false,
                "extraContext": false,
                "sortOrder": "alphabetical"
              },
              "icon": "lucide-search",
              "title": "Search"
            }
          },
          {
            "id": "f343e85d32ce4b84",
            "type": "leaf",
            "state": {
              "type": "bookmarks",
              "state": {},
              "icon": "lucide-bookmark",
              "title": "Bookmarks"
            }
          }
        ]
      }
    ],
    "direction": "horizontal",
    "width": 200
  },
  "right": {
    "id": "92d3d49a8fcd25cd",
    "type": "split",
    "children": [
      {
        "id": "8f5eb341760c7d23",
        "type": "tabs",
        "children": [
          {
            "id": "2c6a4cd13bc77c1e",
            "type": "leaf",
            "state": {
              "type": "backlink",
              "state": {
                "collapseAll": false,
                "extraContext": false,
                "sortOrder": "alphabetical",
                "showSearch": false,
                "searchQuery": "",
                "backlinkCollapsed": false,
                "unlinkedCollapsed": true
              },
              "icon": "links-coming-in",
              "title": "Backlinks"
            }
          },
          {
            "id": "5199aec6acb6f431",
            "type": "leaf",
            "state": {
              "type": "outgoing-link",
              "state": {
                "linksCollapsed": false,
                "unlinkedCollapsed": true
              },
              "icon": "links-going-out",
              "title": "Outgoing links"
            }
          },
          {
            "id": "421b263f367a1cdd",
            "type": "leaf",
            "state": {
              "type": "tag",
              "state": {
                "sortOrder": "frequency",
                "useHierarchy": true
              },
              "icon": "lucide-tags",
              "title": "Tags"
            }
          },
          {
            "id": "d78ee1bd2cc1c376",
            "type": "leaf",
            "state": {
              "type": "outline",
              "state": {},
              "icon": "lucide-list",
              "title": "Outline"
            }
          },
          {
            "id": "43ca24d8c31f3009",
            "type": "leaf",
            "state": {
              "type": "git-view",
              "state": {},
              "icon": "git-pull-request",
              "title": "Source Control"
            }
          }
        ],
        "currentTab": 4
      }
    ],
    "direction": "horizontal",
    "width": 300
  },
  "left-ribbon": {
    "hiddenItems": {
      "switcher:Open quick switcher": false,
      "graph:Open graph view": false,
      "canvas:Create new canvas": false,
      "daily-notes:Open today's daily note": false,
      "templates:Insert template": false,
      "command-palette:Open command palette": false,
      "obsidian-git:Open Git source control": false
    }
  },
  "active": "cc990617e5bfac50",
  "lastOpenFiles": [
    "서비스 디자이너/CV.md",
    "서비스 디자이너/JD.md",
    "서비스 디자이너/RNR.md",
    "Untitled",
    "개발/스프링을 잘한다의 정의.md",
    "서비스 디자이너",
    "개발",
    "개발/JPA/JPA MindMap.md",
    "개발/스프링과 DI/스프링과 DI.md",
    "개발/JPA/ORM의 문제와 도메인 설계.md",
    "개발/JPA/영속성 컨텍스트와 ORM.md",
    "개발/데이터베이스/샤딩.md",
    "개발/스프링과 DI/스프링과 DI Map.md",
    "개발/스프링과 DI/ApplicationContext.md",
    "개발/스프링과 DI/IoC 컨테이너.md",
    "개발/JPA/JPA의 캐싱(Caching).md",
    "개발/JPA/JPA의 영속성 컨텍스트(Persistence Context).md",
    "개발/JPA/JPA.md",
    "개발/JPA/N+1/N+1 and Custom BatchSize Annotation.md",
    "개발/JPA/N+1/N+1 문제.md",
    "개발/JPA/N+1/EntityGraph in JPA.md",
    "개발/JPA/JPA와 메모리/JPA의 메모리 관리.md",
    "개발/JPA/JPA와 메모리/JPA 메모리 관리법의 장단점 및 적절한 상황.md",
    "개발/processing/논 블로킹 모델의 강력함.md",
    "개발/데이터베이스/트랜잭션 동시성, 데이터 일관성.md",
    "개발/스프링과 DI",
    "개발/JPA/N+1",
    "개발/processing/멀티스레드.md",
    "Untitled.canvas",
    "2024-12-02.md",
    "개발/processing/대규모 트래픽 처리.md",
    "개발/processing/동시성.md",
    "대규모 트래픽 처리",
    "개발/processing",
    "개발",
    "개발/데이터베이스",
    "JPA/JPA와 캐시"
  ]
}